<?xml version="1.0" encoding="UTF-8"?><record_update>
    <sys_choice action="INSERT_OR_UPDATE" field="approval" table="x_1014103_studen_0_registered_students" version="3">
        <sys_choice_set action="INSERT_OR_UPDATE">
            <element>approval</element>
            <name>x_1014103_studen_0_registered_students</name>
            <sys_class_name>sys_choice_set</sys_class_name>
            <sys_created_by>admin</sys_created_by>
            <sys_created_on>2023-04-03 11:09:26</sys_created_on>
            <sys_mod_count>0</sys_mod_count>
            <sys_name>approval</sys_name>
            <sys_package display_value="Student registration" source="x_1014103_studen_0">3d2d5b1497022110ca43d6081153afef</sys_package>
            <sys_policy/>
            <sys_scope display_value="Student registration">3d2d5b1497022110ca43d6081153afef</sys_scope>
            <sys_update_name>sys_choice_x_1014103_studen_0_registered_students_approval</sys_update_name>
            <sys_updated_by>admin</sys_updated_by>
            <sys_updated_on>2023-04-03 11:09:26</sys_updated_on>
        </sys_choice_set>
    </sys_choice>
</record_update>
